pimetrics/__init__.py
pimetrics/probe.py
pimetrics/version.py
pimetrics-0.1.4.dist-info/LICENSE.md
pimetrics-0.1.4.dist-info/METADATA
pimetrics-0.1.4.dist-info/WHEEL
pimetrics-0.1.4.dist-info/top_level.txt
pimetrics-0.1.4.dist-info/RECORD
