Metadata-Version: 2.1
Name: pimetrics
Version: 0.1.4
Summary: Metrics to measure data from different sources and report to a monitoring system (e.g. Prometheus)
Home-page: https://github.com/clambin/pimetrics
Author: Christophe Lambin
Author-email: christophe.lambin@gmail.com
License: UNKNOWN
Platform: UNKNOWN
Classifier: Programming Language :: Python :: 3
Classifier: License :: OSI Approved :: MIT License
Classifier: Operating System :: OS Independent
Requires-Python: >=3.7
